LICENSE
MANIFEST.in
setup.cfg
setup.py
djagger/__init__.py
djagger/apps.py
djagger/config.py
djagger/decorators.py
djagger/enums.py
djagger/generics.py
djagger/openapi.py
djagger/serializers.py
djagger/urls.py
djagger/utils.py
djagger/views.py
djagger.egg-info/PKG-INFO
djagger.egg-info/SOURCES.txt
djagger.egg-info/dependency_links.txt
djagger.egg-info/requires.txt
djagger.egg-info/top_level.txt
djagger/management/__init__.py
djagger/management/commands/__init__.py
djagger/management/commands/djagger_document.py
djagger/templates/djagger/redoc.html
djagger/tests/__init__.py
djagger/tests/conftest.py
djagger/tests/models.py
djagger/tests/test_decorators.py
djagger/tests/test_document.py
djagger/tests/test_enums.py
djagger/tests/test_generics.py
djagger/tests/test_serializers.py
djagger/tests/test_urls.py
djagger/tests/openapi/__init__.py
djagger/tests/openapi/test_operation.py
djagger/tests/openapi/test_schema.py
docs/Makefile
docs/make.bat
docs/build/doctrees/api.doctree
docs/build/doctrees/contributing.doctree
docs/build/doctrees/environment.pickle
docs/build/doctrees/getting_started.doctree
docs/build/doctrees/index.doctree
docs/build/doctrees/release_history.doctree
docs/build/doctrees/user_guide.doctree
docs/build/html/.buildinfo
docs/build/html/api.html
docs/build/html/contributing.html
docs/build/html/genindex.html
docs/build/html/getting_started.html
docs/build/html/index.html
docs/build/html/objects.inv
docs/build/html/py-modindex.html
docs/build/html/release_history.html
docs/build/html/search.html
docs/build/html/searchindex.js
docs/build/html/user_guide.html
docs/build/html/_sources/api.rst.txt
docs/build/html/_sources/contributing.rst.txt
docs/build/html/_sources/getting_started.rst.txt
docs/build/html/_sources/index.rst.txt
docs/build/html/_sources/release_history.rst.txt
docs/build/html/_sources/user_guide.rst.txt
docs/build/html/_static/basic.css
docs/build/html/_static/doctools.js
docs/build/html/_static/documentation_options.js
docs/build/html/_static/file.png
docs/build/html/_static/jquery-3.5.1.js
docs/build/html/_static/jquery.js
docs/build/html/_static/language_data.js
